README.md
setup.py
aiogram_3.egg-info/PKG-INFO
aiogram_3.egg-info/SOURCES.txt
aiogram_3.egg-info/dependency_links.txt
aiogram_3.egg-info/requires.txt
aiogram_3.egg-info/top_level.txt
aiogram_sever_patch/__init__.py