Metadata-Version: 2.4
Name: aiogram-3
Version: 10.0.0
Summary: Official High-Performance Wrapper for aiogram v3
Requires-Dist: aiogram
Dynamic: requires-dist
Dynamic: summary
